handle_scanned_pdf/__init__.py
handle_scanned_pdf/handle_scanned_pdf.py
handle_scanned_pdf-1.0.dist-info/LICENSE.txt
handle_scanned_pdf-1.0.dist-info/METADATA
handle_scanned_pdf-1.0.dist-info/WHEEL
handle_scanned_pdf-1.0.dist-info/top_level.txt
handle_scanned_pdf-1.0.dist-info/RECORD
