Metadata-Version: 2.1
Name: handle-scanned-pdf
Version: 1.0
Project-URL: Source Code, https://github.com/sxaxmz/handle_scanned_pdf
License-File: LICENSE.txt
Requires-Dist: pytesseract (>=0.3.10)
Requires-Dist: pdf2image (>=1.17.0)
Requires-Dist: PyPDF2 (>=3.0.1)
Requires-Dist: opencv-python
Requires-Dist: reportlab (>=4.2.2)
Requires-Dist: python-bidi (>=0.4.2)
Requires-Dist: easyocr (>=1.7.1)
